SynGenes/SynGenes.py
SynGenes/__init__.py
SynGenes-1.1.0.dist-info/LICENSE
SynGenes-1.1.0.dist-info/METADATA
SynGenes-1.1.0.dist-info/WHEEL
SynGenes-1.1.0.dist-info/top_level.txt
SynGenes-1.1.0.dist-info/RECORD
