Metadata-Version: 2.1
Name: SynGenes
Version: 1.1.0
Summary: SynGenes is a Python class for standardizing mitochondrial/chloroplast gene nomenclatures.
Home-page: https://github.com/luanrabelo/SynGenes
Download-URL: https://github.com/luanrabelo/SynGenes
Author: Luan Rabelo
Author-email: luanrabelo@outlook.com
Maintainer: Luan Rabelo
Maintainer-email: luanrabelo@outlook.com
License: MIT License
Keywords: SynGenes Genes Bioinformatics Synonymous
Classifier: Development Status :: 5 - Production/Stable
Classifier: Intended Audience :: Science/Research
Classifier: Environment :: Web Environment
Classifier: Topic :: Scientific/Engineering :: Bio-Informatics
Classifier: License :: OSI Approved :: MIT License
Classifier: Programming Language :: Python :: 3.7
Classifier: Operating System :: Microsoft :: Windows
Classifier: Operating System :: MacOS :: MacOS X
Classifier: Operating System :: POSIX :: Linux
License-File: LICENSE
Requires-Dist: requests
Requires-Dist: pandas
Requires-Dist: openpyxl
